core_evals/tooltalk/__init__.py
core_evals/tooltalk/framework.yml
core_evals/tooltalk/framework_entrypoint.py
core_evals/tooltalk/output.py
nvidia_tooltalk-25.11.dist-info/licenses/LICENSE
nvidia_tooltalk-25.11.dist-info/licenses/NOTICE
tooltalk/__init__.py
tooltalk/apis/__init__.py
tooltalk/apis/account.py
tooltalk/apis/alarm.py
tooltalk/apis/api.py
tooltalk/apis/calendar.py
tooltalk/apis/email.py
tooltalk/apis/exceptions.py
tooltalk/apis/message.py
tooltalk/apis/reminder.py
tooltalk/apis/utils.py
tooltalk/apis/weather.py
tooltalk/data/databases/Account.json
tooltalk/data/databases/Alarm.json
tooltalk/data/databases/Calendar.json
tooltalk/data/databases/Email.json
tooltalk/data/databases/HistoricWeather.json
tooltalk/data/databases/Message.json
tooltalk/data/databases/Reminder.json
tooltalk/data/databases/Weather.json
tooltalk/data/easy/AddAlarm-easy.json
tooltalk/data/easy/AddReminder-easy.json
tooltalk/data/easy/ChangePassword-easy.json
tooltalk/data/easy/CompleteReminder-easy.json
tooltalk/data/easy/CreateEvent-easy.json
tooltalk/data/easy/CurrentWeather-easy.json
tooltalk/data/easy/DeleteAccount-easy.json
tooltalk/data/easy/DeleteAlarm-easy.json
tooltalk/data/easy/DeleteEvent-easy.json
tooltalk/data/easy/DeleteReminder-easy.json
tooltalk/data/easy/FindAlarms-easy.json
tooltalk/data/easy/ForecastWeather-easy.json
tooltalk/data/easy/GetAccountInformation-easy.json
tooltalk/data/easy/GetReminders-easy.json
tooltalk/data/easy/HistoricWeather-easy.json
tooltalk/data/easy/LogoutUser-easy.json
tooltalk/data/easy/ModifyEvent-easy.json
tooltalk/data/easy/QueryCalendar-easy.json
tooltalk/data/easy/QueryUser-easy.json
tooltalk/data/easy/RegisterUser-easy.json
tooltalk/data/easy/ResetPassword-easy.json
tooltalk/data/easy/SearchInbox-easy.json
tooltalk/data/easy/SearchMessages-easy.json
tooltalk/data/easy/SendEmail-easy.json
tooltalk/data/easy/SendMessage-easy.json
tooltalk/data/easy/SendVerificationCode-easy.json
tooltalk/data/easy/UpdateAccountInformation-easy.json
tooltalk/data/easy/UserLogin-easy.json
nvidia_tooltalk-25.11.dist-info/METADATA
nvidia_tooltalk-25.11.dist-info/WHEEL
nvidia_tooltalk-25.11.dist-info/entry_points.txt
nvidia_tooltalk-25.11.dist-info/top_level.txt
nvidia_tooltalk-25.11.dist-info/RECORD
