Metadata-Version: 2.4
Name: nvidia_tooltalk
Version: 25.11
Summary: Evaluating tool-augmented LLMs in a conversational setting - packaged by NVIDIA
License: MIT
Classifier: Development Status :: 5 - Production/Stable
Classifier: Programming Language :: Python :: 3
Classifier: License :: OSI Approved :: MIT License
Classifier: Operating System :: OS Independent
Requires-Python: >=3.8
License-File: LICENSE
License-File: NOTICE
Requires-Dist: tqdm
Requires-Dist: numpy
Requires-Dist: matplotlib
Requires-Dist: openai
Requires-Dist: pytest
Requires-Dist: torch
Requires-Dist: transformers
Requires-Dist: nemo-evaluator
Dynamic: classifier
Dynamic: description
Dynamic: description-content-type
Dynamic: license
Dynamic: license-file
Dynamic: requires-dist
Dynamic: requires-python
Dynamic: summary
